OSRS_Hiscores/__init__.py
OSRS_Hiscores-0.3.dist-info/LICENSE
OSRS_Hiscores-0.3.dist-info/METADATA
OSRS_Hiscores-0.3.dist-info/WHEEL
OSRS_Hiscores-0.3.dist-info/top_level.txt
OSRS_Hiscores-0.3.dist-info/RECORD
