Metadata-Version: 2.1
Name: OSRS-Hiscores
Version: 0.3
Summary: An Old School Runescape (OSRS) Hiscore Library
Home-page: https://github.com/Coffee-fueled-deadlines/osrs-hiscores
Author: Coffee Fueled Deadlines
Author-email: cookm0803@gmail.com
License: UNKNOWN
Platform: UNKNOWN
Classifier: Programming Language :: Python :: 3
Classifier: License :: OSI Approved :: MIT License
Classifier: Operating System :: OS Independent
